{"results": {"dataframe_schema.Decorators.time_check_input": {"result": [7.048947333772239e-06], "stats": [{"ci_99": [6.994622119815669e-06, 7.25416984858464e-06], "q_25": 7.0310098749176875e-06, "q_75": 7.1421540487162826e-06, "min": 6.994622119815669e-06, "max": 7.25416984858464e-06, "mean": 7.0904500987491856e-06, "std": 9.093907552272335e-08, "repeat": 10, "number": 1519}]}, "dataframe_schema.Decorators.time_check_output": {"result": [7.071794776119392e-06], "stats": [{"ci_99": [6.954863636363683e-06, 8.023296472184582e-06], "q_25": 7.0182137042062345e-06, "q_75": 7.23383904341926e-06, "min": 6.954863636363683e-06, "max": 8.023296472184582e-06, "mean": 7.1946464721845385e-06, "std": 3.024896609861874e-07, "repeat": 10, "number": 1474}]}, "dataframe_schema.Validate.time_df_schema": {"result": [0.007374578999999992], "stats": [{"ci_99": [0.00721889600000003, 0.00800562699999996], "q_25": 0.007259183374999978, "q_75": 0.007709520124999994, "min": 0.00721889600000003, "max": 0.00800562699999996, "mean": 0.007487139899999995, "std": 0.000268414211457287, "repeat": 10, "number": 2}]}, "series_schema.Validate.time_series_schema": {"result": [0.0006617953437500004], "stats": [{"ci_99": [0.0006550513125000018, 0.000670112437500002], "q_25": 0.0006580591093750029, "q_75": 0.0006646706718750027, "min": 0.0006550513125000018, "max": 0.000670112437500002, "mean": 0.0006620263812500013, "std": 4.677488951537732e-06, "repeat": 10, "number": 16}]}, "dataframe_schema.Decorators.mem_check_input": 0, "dataframe_schema.Decorators.mem_check_output": 0, "dataframe_schema.Decorators.peakmem_check_input": 69390336, "dataframe_schema.Decorators.peakmem_check_output": 69419008, "dataframe_schema.Validate.mem_df_schema": 0, "dataframe_schema.Validate.peakmem_df_schema": 70139904, "series_schema.Validate.mem_series_schema": 0, "series_schema.Validate.peakmem_series_schema": 69423104}, "params": {"arch": "x86_64", "cpu": "Intel(R) Core(TM) i7-4850HQ CPU @ 2.30GHz", "machine": "NM_MBP_15_2013", "num_cpu": "8", "os": "Darwin 19.2.0", "ram": "17179869184", "python": "3.8", "numpy": "", "pandas": "", "scipy": "", "wrapt": ""}, "requirements": {"numpy": "", "pandas": "", "scipy": "", "wrapt": ""}, "commit_hash": "e6782f1cb213ed3135fb30768c8edf1c6fa8c536", "date": 1568079668000, "env_name": "conda-py3.8-numpy-pandas-scipy-wrapt", "python": "3.8", "profiles": {}, "started_at": {"dataframe_schema.Decorators.time_check_input": 1578777367292, "dataframe_schema.Decorators.time_check_output": 1578777368190, "dataframe_schema.Validate.time_df_schema": 1578777370570, "series_schema.Validate.time_series_schema": 1578777372957, "dataframe_schema.Decorators.mem_check_input": 1578777364341, "dataframe_schema.Decorators.mem_check_output": 1578777365081, "dataframe_schema.Decorators.peakmem_check_input": 1578777365817, "dataframe_schema.Decorators.peakmem_check_output": 1578777366558, "dataframe_schema.Validate.mem_df_schema": 1578777369081, "dataframe_schema.Validate.peakmem_df_schema": 1578777369828, "series_schema.Validate.mem_series_schema": 1578777371484, "series_schema.Validate.peakmem_series_schema": 1578777372211}, "ended_at": {"dataframe_schema.Decorators.time_check_input": 1578777368190, "dataframe_schema.Decorators.time_check_output": 1578777369081, "dataframe_schema.Validate.time_df_schema": 1578777371484, "series_schema.Validate.time_series_schema": 1578777373843, "dataframe_schema.Decorators.mem_check_input": 1578777365081, "dataframe_schema.Decorators.mem_check_output": 1578777365817, "dataframe_schema.Decorators.peakmem_check_input": 1578777366558, "dataframe_schema.Decorators.peakmem_check_output": 1578777367291, "dataframe_schema.Validate.mem_df_schema": 1578777369828, "dataframe_schema.Validate.peakmem_df_schema": 1578777370570, "series_schema.Validate.mem_series_schema": 1578777372211, "series_schema.Validate.peakmem_series_schema": 1578777372957}, "benchmark_version": {"dataframe_schema.Decorators.time_check_input": "4fd77a899e76c5aa41154a6ce315111de59d38e5e6412f7fca3ee4d153f8c32b", "dataframe_schema.Decorators.time_check_output": "f7514d87e969c54d82e4997e96d35fabe056e5ae18b83a6767b5cd62df9d4494", "dataframe_schema.Validate.time_df_schema": "2f71e2645cea81a3ce8fb632321fb122d7b758bb153c1098bcd3dc35acd12b87", "series_schema.Validate.time_series_schema": "600cc36ac19c30710095722d4090e9c2c3f00be7945ba8ef3655a7b2ebb9c4e3", "dataframe_schema.Decorators.mem_check_input": "3ea697ffff289f33f269332640cc7c528ffb275ef229da091c885b11e28ccd49", "dataframe_schema.Decorators.mem_check_output": "ed1435e8c6947a3d94dadfc85eee5581e5d195fd29a0e91f51e231c59aeb4fee", "dataframe_schema.Decorators.peakmem_check_input": "67ded5ba2108b9bca264b48b535548b68b5199261d5b146163a37ce6d914ca74", "dataframe_schema.Decorators.peakmem_check_output": "45dd4f4c48273b8c1d0f837e81679ee4d0e1995c327206276cc32743368842e9", "dataframe_schema.Validate.mem_df_schema": "23089f5ca9c3daebe660e72445237be641594be9680900994f53cfe47fc85d4a", "dataframe_schema.Validate.peakmem_df_schema": "5ea67a5ea14055b175ca1cf4c7f3b213f9057da562d6baebaccb8b667c31ecc4", "series_schema.Validate.mem_series_schema": "d640c3be054a1d4dd88af6aac36c6b9c3e1ae4811dba553777e4854e0b940521", "series_schema.Validate.peakmem_series_schema": "69f2d835b0e4ff61ca789892cb0f3df2f517640816c1dbe6df7419c13760c341"}, "version": 1}